LICENSE
MANIFEST.in
README
setup.py
django_sms_validator.egg-info/PKG-INFO
django_sms_validator.egg-info/SOURCES.txt
django_sms_validator.egg-info/dependency_links.txt
django_sms_validator.egg-info/not-zip-safe
django_sms_validator.egg-info/requires.txt
django_sms_validator.egg-info/top_level.txt
sms_validator/__init__.py
sms_validator/config.py
sms_validator/models.py
sms_validator/version.py
sms_validator/locale/cs/LC_MESSAGES/django.mo
sms_validator/locale/cs/LC_MESSAGES/django.po
sms_validator/management/__init__.py
sms_validator/management/commands/__init__.py
sms_validator/management/commands/clean_sms_validator_tokens.py
sms_validator/migrations/0001_initial.py
sms_validator/migrations/__init__.py