Metadata-Version: 1.1
Name: django-sms-validator
Version: 0.2.4
Summary: Python library for sms validation.
Home-page: https://github.com/matllubos/sms-validator
Author: Lubos Matl
Author-email: matllubos@gmail.com
License: LGPL
Keywords: django,sms,python
Platform: UNKNOWN
Classifier: Development Status :: 3 - Alpha
Classifier: Environment :: Web Environment
Classifier: Framework :: Django
Classifier: Intended Audience :: Developers
Classifier: Intended Audience :: End Users/Desktop
Classifier: License :: OSI Approved :: BSD License
Classifier: Natural Language :: Czech
Classifier: Operating System :: OS Independent
Classifier: Programming Language :: Python
Classifier: Topic :: Internet :: WWW/HTTP :: Dynamic Content
Classifier: Topic :: Internet :: WWW/HTTP :: Site Management
